MIPS32.v

module pipe_MIPS32(clk1, clk2);
   
   input clk1, clk2;        //TWO Phase Clock
   reg [31:0] PC, IF_ID_IR,IF_ID_NPC;
   reg [31:0] ID_EX_IR, ID_EX_NPC, ID_EX_A, ID_EX_B, ID_EX_Imm;
   reg [2:0] ID_EX_type, EX_MEM_type, MEM_WB_type;
   reg [31:0] EX_MEM_IR, EX_MEM_ALUOut, EX_MEM_B;
   reg        EX_MEM_cond;                          //branch cond check
   reg [31:0] MEM_WB_IR, MEM_WB_ALUOut, MEM_WB_LMD;
   
   reg [31:0] Reg [0:31];       //Register bank 32x32
   reg [31:0] Mem [0:1023];     //1024x32 bit Memory
   
   parameter ADD=6'b000000, SUB=6'b000001, AND=6'b000010, OR=6'b000011, 
             SLT=6'b000100, MUL=6'b000101, HLT=6'b111111, LW=6'b001000,     //Store less than
             SW=6'b001001, ADDI=6'b001010, SUBI=6'b001011, SLTI=6'b001100,
             BNEQZ=6'b001101, BEQZ=6'b001110;   
   
   parameter RR_ALU=3'b000, RM_ALU=3'b001, LOAD=3'b010, STORE=3'b011, 
             BRANCH=3'b100, HALT=3'b101;
   reg HALTED;  //set after hlt instruction to terminate previous running inst(in WB stage)
   reg TAKEN_BRANCH;  //required to disable inst after branch
   
   always @(posedge clk1)          //IF stage
        if (HALTED==0)
        begin
            if(((EX_MEM_IR[31:26]==BEQZ) && (EX_MEM_cond==1)) ||    //cond=1 if A is 0
               ((EX_MEM_IR[31:26]==BNEQZ) && (EX_MEM_cond==0)))   //register A not zero
                begin
                 IF_ID_IR       <= #2   Mem[EX_MEM_ALUOut];
                 TAKEN_BRANCH   <= #2   1'b1;
                 IF_ID_NPC      <= #2   EX_MEM_ALUOut + 1;
                 PC             <= #2   EX_MEM_ALUOut + 1;
                end
            else 
            begin
                    IF_ID_IR    <= #2 Mem[PC];
                    IF_ID_NPC   <= #2 PC+1;
                    PC          <= #2 PC+1;
                end
         end
         
    always @(posedge clk2)          //ID stage
        if (HALTED==0)
        begin
            if (IF_ID_IR[25:21] == 5'b00000)    
            ID_EX_A<=0;
            else 
            ID_EX_A    <=  #2 Reg[IF_ID_IR[25:21]];    //rs(source register)
            
            if (IF_ID_IR[20:16] == 5'b00000)    ID_EX_B<=0;
            else ID_EX_B    <=  #2 Reg[IF_ID_IR[20:16]];     //rt
            
            ID_EX_NPC   <= #2   IF_ID_NPC;
            ID_EX_IR    <= #2   IF_ID_IR;
            ID_EX_Imm   <= #2   {{16{IF_ID_IR[15]}}, {IF_ID_IR[15:0]}}; //signed extension replicate
            
            case (IF_ID_IR[31:26])
                ADD,SUB,AND,OR,SLT,MUL: ID_EX_type    <= #2 RR_ALU;
                ADDI,SUBI,SLTI        : ID_EX_type    <= #2 RM_ALU;
                LW:                     ID_EX_type    <= #2 LOAD;
                SW:                     ID_EX_type    <= #2 STORE;
                BNEQZ,BEQZ:             ID_EX_type    <= #2 BRANCH;
                HLT:                    ID_EX_type    <= #2 HALT;
                default:                ID_EX_type    <= #2 HALT;       //INVALID OPCODE
             endcase
          end
          
       always @(posedge clk1)              //EX stage                  
          if(HALTED==0)
            begin
                EX_MEM_IR <= #2 ID_EX_IR;
                EX_MEM_type <= #2 ID_EX_type;
                TAKEN_BRANCH <= #2 0;
                
                case(ID_EX_type)
                RR_ALU: begin
                    case(ID_EX_IR[31:26]) 
                    ADD : EX_MEM_ALUOut <= #2 ID_EX_A + ID_EX_B;
                    SUB : EX_MEM_ALUOut <= #2  ID_EX_A - ID_EX_B;
                    OR : EX_MEM_ALUOut <= #2  ID_EX_A | ID_EX_B;
                    MUL : EX_MEM_ALUOut <= #2  ID_EX_A * ID_EX_B;
                    SLT : EX_MEM_ALUOut <= #2  ID_EX_A < ID_EX_B;
                    AND : EX_MEM_ALUOut <= #2  ID_EX_A & ID_EX_B;
                    default : EX_MEM_ALUOut <= #2  32'hx;
                 endcase
            end
                RM_ALU: begin
                case(ID_EX_IR[31:26])
                ADDI:   EX_MEM_ALUOut <= #2 ID_EX_A + ID_EX_Imm;
                SUBI:   EX_MEM_ALUOut <= #2  ID_EX_A - ID_EX_Imm;
                SLTI:   EX_MEM_ALUOut <= #2  ID_EX_A < ID_EX_Imm;
                default:  EX_MEM_ALUOut <=#2 32'hx;
                endcase
                end
                
                LOAD,STORE:
                    begin
                    EX_MEM_ALUOut <= #2 ID_EX_A + ID_EX_Imm;
                    EX_MEM_B      <= #2 ID_EX_B;
                    end
                BRANCH: begin
                    EX_MEM_ALUOut <= #2 ID_EX_NPC + ID_EX_Imm;
                    EX_MEM_cond   <= #2 (ID_EX_A==0);
                    end
                endcase
             end
        always @(posedge clk2)        //MEM stage
            if(HALTED==0) begin
                MEM_WB_type <= #2 EX_MEM_type;
                MEM_WB_IR   <= #2 EX_MEM_IR;
                
                    case (EX_MEM_type)
                    RR_ALU,RM_ALU:  MEM_WB_ALUOut <= #2 EX_MEM_ALUOut;
                    LOAD:           MEM_WB_LMD<= #2 Mem[EX_MEM_ALUOut];
                    STORE:
                        if (TAKEN_BRANCH==0)
                            Mem[EX_MEM_ALUOut] <= #2 EX_MEM_B;
                     endcase
                     end
           
          always @(posedge clk1)        //WB Stage
            begin if(TAKEN_BRANCH==0)
                case(MEM_WB_type)
                    RR_ALU: Reg[MEM_WB_IR[15:11]] <= #2 MEM_WB_ALUOut;  //rd
                    RM_ALU: Reg[MEM_WB_IR[20:16]] <= #2 MEM_WB_ALUOut;   //rt
                    LOAD:   Reg[MEM_WB_IR[20:16]] <= #2 MEM_WB_LMD;      //rt
                    HALT:   HALTED <= #2 1'b1;
                    endcase
                    end    
                 
endmodule

Test_Bench1.v
`include "MIPS32.v"

module test1_mips32;
reg clk1, clk2;
    integer k;
pipe_MIPS32 mips(clk1, clk2);
    initial
    begin
        clk1=0; clk2=0;
         repeat(50) begin
    #5 clk1=1; #5 clk1=0;
    #5 clk2=1; #5 clk2=0;
    end
end

initial
begin
  for (k=0; k<31; k++) mips.Reg[k] = k;

  mips.Mem[0]  =  32'h2801000a;  // ADDI R1, R0, 10
  mips.Mem[1]  =  32'h28020014;  // ADDI R2, R0, 20
  mips.Mem[2]  =  32'h28030019;  // ADDI R3, R0, 25
  mips.Mem[3]  =  32'h0ce77800;  // OR   R7, R7, R7  -- Dummy instr.
  mips.Mem[4]  =  32'h0ce77800;  // OR   R7, R7, R7  -- Dummy instr.
  mips.Mem[5]  =  32'h00222000;  // ADD  R4, R1, R2  
  mips.Mem[6]  =  32'h0ce77800;  // OR   R7, R7, R7  -- Dummy instr.
  mips.Mem[7]  =  32'h00832800;  // ADD  R5, R4, R3
  mips.Mem[8]  =  32'hfc000000;  // HLT
  mips.HALTED  =  0;
  mips.PC      =  0;
  mips.TAKEN_BRANCH = 0;
  
  #280
  for (k=0;k<6;k++) $display ("R%1d - %2d", k, mips.Reg[k]);
end

initial
begin
  $dumpfile ("mips.vcd");
  $dumpvars (0, test1_mips32);
  #300 $finish;
end
 
endmodule

Test/test2/mips2.vcd
$date
	Mon Sep 16 01:34:47 2024
$end
$version
	Icarus Verilog
$end
$timescale
	1s
$end
$scope module test1_mips32 $end
$var reg 1 ! clk1 $end
$var reg 1 " clk2 $end
$var integer 32 # k [31:0] $end
$scope module mips $end
$var wire 1 ! clk1 $end
$var wire 1 " clk2 $end
$var parameter 6 $ ADD $end
$var parameter 6 % ADDI $end
$var parameter 6 & AND $end
$var parameter 6 ' BEQZ $end
$var parameter 6 ( BNEQZ $end
$var parameter 3 ) BRANCH $end
$var parameter 3 * HALT $end
$var parameter 6 + HLT $end
$var parameter 3 , LOAD $end
$var parameter 6 - LW $end
$var parameter 6 . MUL $end
$var parameter 6 / OR $end
$var parameter 3 0 RM_ALU $end
$var parameter 3 1 RR_ALU $end
$var parameter 6 2 SLT $end
$var parameter 6 3 SLTI $end
$var parameter 3 4 STORE $end
$var parameter 6 5 SUB $end
$var parameter 6 6 SUBI $end
$var parameter 6 7 SW $end
$var reg 32 8 EX_MEM_ALUOut [31:0] $end
$var reg 32 9 EX_MEM_B [31:0] $end
$var reg 32 : EX_MEM_IR [31:0] $end
$var reg 1 ; EX_MEM_cond $end
$var reg 3 < EX_MEM_type [2:0] $end
$var reg 1 = HALTED $end
$var reg 32 > ID_EX_A [31:0] $end
$var reg 32 ? ID_EX_B [31:0] $end
$var reg 32 @ ID_EX_IR [31:0] $end
$var reg 32 A ID_EX_Imm [31:0] $end
$var reg 32 B ID_EX_NPC [31:0] $end
$var reg 3 C ID_EX_type [2:0] $end
$var reg 32 D IF_ID_IR [31:0] $end
$var reg 32 E IF_ID_NPC [31:0] $end
$var reg 32 F MEM_WB_ALUOut [31:0] $end
$var reg 32 G MEM_WB_IR [31:0] $end
$var reg 32 H MEM_WB_LMD [31:0] $end
$var reg 3 I MEM_WB_type [2:0] $end
$var reg 32 J PC [31:0] $end
$var reg 1 K TAKEN_BRANCH $end
$upscope $end
$upscope $end
$enddefinitions $end
$comment Show the parameter values. $end
$dumpall
b1001 7
b1011 6
b1 5
b11 4
b1100 3
b100 2
b0 1
b1 0
b11 /
b101 .
b1000 -
b10 ,
b111111 +
b101 *
b100 )
b1101 (
b1110 '
b10 &
b1010 %
b0 $
$end
#0
$dumpvars
0K
b0 J
bx I
bx H
bx G
bx F
bx E
bx D
bx C
bx B
bx A
bx @
bx ?
bx >
0=
bx <
x;
bx :
bx 9
bx 8
b11111 #
0"
0!
$end
#5
1!
#7
b1 J
b1 E
b101000000000010000000001111000 D
#10
0!
#15
b0 >
1"
#17
b1 C
b1111000 A
b101000000000010000000001111000 @
b1 B
b1 ?
#20
0"
#25
1!
#27
b1111000 8
b1 <
b101000000000010000000001111000 :
b10 J
b10 E
b1100011000110001100000000000 D
#30
0!
#35
1"
#37
b1111000 F
b101000000000010000000001111000 G
b1 I
b0 C
b1100000000000 A
b1100011000110001100000000000 @
b10 B
b11 ?
b11 >
#40
0"
#45
1!
#47
b11 J
b11 E
b100000001000100000000000000000 D
b11 8
b0 <
b1100011000110001100000000000 :
#50
0!
#55
1"
#57
b10 C
b0 A
b100000001000100000000000000000 @
b11 B
b10 ?
b1111000 >
b11 F
b1100011000110001100000000000 G
b0 I
#60
0"
#65
1!
#67
b10 9
b1111000 8
b10 <
b100000001000100000000000000000 :
b100 J
b100 E
b1100011000110001100000000000 D
#70
0!
#75
1"
#77
b1010101 H
b100000001000100000000000000000 G
b10 I
b0 C
b1100000000000 A
b1100011000110001100000000000 @
b100 B
b11 ?
b11 >
#80
0"
#85
1!
#87
b101 J
b101 E
b101000010000100000000000101101 D
b11 8
b0 <
b1100011000110001100000000000 :
#90
0!
#95
1"
#97
b1 C
b101101 A
b101000010000100000000000101101 @
b101 B
b1010101 ?
b1010101 >
b1100011000110001100000000000 G
b0 I
#100
0"
#105
1!
#107
b10000010 8
b1 <
b101000010000100000000000101101 :
b110 J
b110 E
b1100011000110001100000000000 D
#110
0!
#115
1"
#117
b10000010 F
b101000010000100000000000101101 G
b1 I
b0 C
b1100000000000 A
b1100011000110001100000000000 @
b110 B
b11 ?
b11 >
#120
0"
#125
1!
#127
b111 J
b111 E
b100100001000100000000000000001 D
b11 8
b0 <
b1100011000110001100000000000 :
#130
0!
#135
1"
#137
b11 C
b1 A
b100100001000100000000000000001 @
b111 B
b10000010 ?
b1111000 >
b11 F
b1100011000110001100000000000 G
b0 I
#140
0"
#145
1!
#147
b10000010 9
b1111001 8
b11 <
b100100001000100000000000000001 :
b1000 J
b1000 E
b11111100000000000000000000000000 D
#150
0!
#155
b0 ?
b0 >
1"
#157
b100100001000100000000000000001 G
b11 I
b101 C
b0 A
b11111100000000000000000000000000 @
b1000 B
#160
0"
#165
1!
#167
b1001 J
b1001 E
bx D
b101 <
b11111100000000000000000000000000 :
#170
0!
#175
1"
#177
bx A
bx @
b1001 B
bx ?
bx >
b11111100000000000000000000000000 G
b101 I
#180
0"
#185
1!
#187
1=
bx :
b1010 J
b1010 E
