MIPS32.v

module pipe_MIPS32(clk1, clk2);
   
   input clk1, clk2;        //TWO Phase Clock
   reg [31:0] PC, IF_ID_IR,IF_ID_NPC;
   reg [31:0] ID_EX_IR, ID_EX_NPC, ID_EX_A, ID_EX_B, ID_EX_Imm;
   reg [2:0] ID_EX_type, EX_MEM_type, MEM_WB_type;
   reg [31:0] EX_MEM_IR, EX_MEM_ALUOut, EX_MEM_B;
   reg        EX_MEM_cond;                          //branch cond check
   reg [31:0] MEM_WB_IR, MEM_WB_ALUOut, MEM_WB_LMD;
   
   reg [31:0] Reg [0:31];       //Register bank 32x32
   reg [31:0] Mem [0:1023];     //1024x32 bit Memory
   
   parameter ADD=6'b000000, SUB=6'b000001, AND=6'b000010, OR=6'b000011, 
             SLT=6'b000100, MUL=6'b000101, HLT=6'b111111, LW=6'b001000,     //Store less than
             SW=6'b001001, ADDI=6'b001010, SUBI=6'b001011, SLTI=6'b001100,
             BNEQZ=6'b001101, BEQZ=6'b001110;   
   
   parameter RR_ALU=3'b000, RM_ALU=3'b001, LOAD=3'b010, STORE=3'b011, 
             BRANCH=3'b100, HALT=3'b101;
   reg HALTED;  //set after hlt instruction to terminate previous running inst(in WB stage)
   reg TAKEN_BRANCH;  //required to disable inst after branch
   
   always @(posedge clk1)          //IF stage
        if (HALTED==0)
        begin
            if(((EX_MEM_IR[31:26]==BEQZ) && (EX_MEM_cond==1)) ||    //cond=1 if A is 0
               ((EX_MEM_IR[31:26]==BNEQZ) && (EX_MEM_cond==0)))   //register A not zero
                begin
                 IF_ID_IR       <= #2   Mem[EX_MEM_ALUOut];
                 TAKEN_BRANCH   <= #2   1'b1;
                 IF_ID_NPC      <= #2   EX_MEM_ALUOut + 1;
                 PC             <= #2   EX_MEM_ALUOut + 1;
                end
            else 
            begin
                    IF_ID_IR    <= #2 Mem[PC];
                    IF_ID_NPC   <= #2 PC+1;
                    PC          <= #2 PC+1;
                end
         end
         
    always @(posedge clk2)          //ID stage
        if (HALTED==0)
        begin
            if (IF_ID_IR[25:21] == 5'b00000)    
            ID_EX_A<=0;
            else 
            ID_EX_A    <=  #2 Reg[IF_ID_IR[25:21]];    //rs(source register)
            
            if (IF_ID_IR[20:16] == 5'b00000)    ID_EX_B<=0;
            else ID_EX_B    <=  #2 Reg[IF_ID_IR[20:16]];     //rt
            
            ID_EX_NPC   <= #2   IF_ID_NPC;
            ID_EX_IR    <= #2   IF_ID_IR;
            ID_EX_Imm   <= #2   {{16{IF_ID_IR[15]}}, {IF_ID_IR[15:0]}}; //signed extension replicate
            
            case (IF_ID_IR[31:26])
                ADD,SUB,AND,OR,SLT,MUL: ID_EX_type    <= #2 RR_ALU;
                ADDI,SUBI,SLTI        : ID_EX_type    <= #2 RM_ALU;
                LW:                     ID_EX_type    <= #2 LOAD;
                SW:                     ID_EX_type    <= #2 STORE;
                BNEQZ,BEQZ:             ID_EX_type    <= #2 BRANCH;
                HLT:                    ID_EX_type    <= #2 HALT;
                default:                ID_EX_type    <= #2 HALT;       //INVALID OPCODE
             endcase
          end
          
       always @(posedge clk1)              //EX stage                  
          if(HALTED==0)
            begin
                EX_MEM_IR <= #2 ID_EX_IR;
                EX_MEM_type <= #2 ID_EX_type;
                TAKEN_BRANCH <= #2 0;
                
                case(ID_EX_type)
                RR_ALU: begin
                    case(ID_EX_IR[31:26]) 
                    ADD : EX_MEM_ALUOut <= #2 ID_EX_A + ID_EX_B;
                    SUB : EX_MEM_ALUOut <= #2  ID_EX_A - ID_EX_B;
                    OR : EX_MEM_ALUOut <= #2  ID_EX_A | ID_EX_B;
                    MUL : EX_MEM_ALUOut <= #2  ID_EX_A * ID_EX_B;
                    SLT : EX_MEM_ALUOut <= #2  ID_EX_A < ID_EX_B;
                    AND : EX_MEM_ALUOut <= #2  ID_EX_A & ID_EX_B;
                    default : EX_MEM_ALUOut <= #2  32'hx;
                 endcase
            end
                RM_ALU: begin
                case(ID_EX_IR[31:26])
                ADDI:   EX_MEM_ALUOut <= #2 ID_EX_A + ID_EX_Imm;
                SUBI:   EX_MEM_ALUOut <= #2  ID_EX_A - ID_EX_Imm;
                SLTI:   EX_MEM_ALUOut <= #2  ID_EX_A < ID_EX_Imm;
                default:  EX_MEM_ALUOut <=#2 32'hx;
                endcase
                end
                
                LOAD,STORE:
                    begin
                    EX_MEM_ALUOut <= #2 ID_EX_A + ID_EX_Imm;
                    EX_MEM_B      <= #2 ID_EX_B;
                    end
                BRANCH: begin
                    EX_MEM_ALUOut <= #2 ID_EX_NPC + ID_EX_Imm;
                    EX_MEM_cond   <= #2 (ID_EX_A==0);
                    end
                endcase
             end
        always @(posedge clk2)        //MEM stage
            if(HALTED==0) begin
                MEM_WB_type <= #2 EX_MEM_type;
                MEM_WB_IR   <= #2 EX_MEM_IR;
                
                    case (EX_MEM_type)
                    RR_ALU,RM_ALU:  MEM_WB_ALUOut <= #2 EX_MEM_ALUOut;
                    LOAD:           MEM_WB_LMD<= #2 Mem[EX_MEM_ALUOut];
                    STORE:
                        if (TAKEN_BRANCH==0)
                            Mem[EX_MEM_ALUOut] <= #2 EX_MEM_B;
                     endcase
                     end
           
          always @(posedge clk1)        //WB Stage
            begin if(TAKEN_BRANCH==0)
                case(MEM_WB_type)
                    RR_ALU: Reg[MEM_WB_IR[15:11]] <= #2 MEM_WB_ALUOut;  //rd
                    RM_ALU: Reg[MEM_WB_IR[20:16]] <= #2 MEM_WB_ALUOut;   //rt
                    LOAD:   Reg[MEM_WB_IR[20:16]] <= #2 MEM_WB_LMD;      //rt
                    HALT:   HALTED <= #2 1'b1;
                    endcase
                    end    
                 
endmodule

Test_Bench3.v
`include "MIPS32.v"


module test3_mips32;
    reg clk1, clk2;
    integer k;
pipe_MIPS32 mips(clk1, clk2);
    initial
    begin
        clk1=0; clk2=0;
         repeat(50) begin
    #5 clk1=1; #5 clk1=0;
    #5 clk2=1; #5 clk2=0;
    end
end
initial
begin
    for(k=0; k<31; k=k+1)
        mips.Reg[k]=k;
        
        mips.Mem[0]=32'h280a00c8;       //ADDI R10, R0, 200
        mips.Mem[1]=32'h28020001;       //ADDI R2, R0, 1
        mips.Mem[2]=32'h0e94a000;       //OR R20, R20, R20--Dummy inst
        mips.Mem[3]=32'h21430000;       //LW R3, 0(R10)
        mips.Mem[4]=32'h0e94a000;       //OR R20, R20, R20--Dummy inst
        mips.Mem[5]=32'h14431000;       //LOOP: MUL R2, R2, R3
        mips.Mem[6]=32'h2c630001;       //SUBI R3, R3, 1
        mips.Mem[7]=32'h0e94a000;       
        mips.Mem[8]=32'h3460fffc;       //BNEQZ R3,Loop(ie -4 offset because PC is at mem9)
        mips.Mem[9]=32'h2542fffe;       //SW R2, -2(R10)
        mips.Mem[10]=32'hfc000000;      //HLT
        
        mips.Mem[200]=7;  //Facrorial of 7
        
        mips.PC=0;
        mips.HALTED=0;
        mips.TAKEN_BRANCH=0;
        
        
        end
initial 
begin
    $dumpfile("mips.vcd");
    $dumpvars(0, test3_mips32);
    $monitor("R2: %4d", mips.Reg[2]);
    $display("Mem[198] = %2d", mips.Mem[198]);

    #3000 $finish;
    end
endmodule

build/mips.vcd
$date
	Mon Sep 16 01:53:12 2024
$end
$version
	Icarus Verilog
$end
$timescale
	1s
$end
$scope module test3_mips32 $end
$var reg 1 ! clk1 $end
$var reg 1 " clk2 $end
$var integer 32 # k [31:0] $end
$scope module mips $end
$var wire 1 ! clk1 $end
$var wire 1 " clk2 $end
$var parameter 6 $ ADD $end
$var parameter 6 % ADDI $end
$var parameter 6 & AND $end
$var parameter 6 ' BEQZ $end
$var parameter 6 ( BNEQZ $end
$var parameter 3 ) BRANCH $end
$var parameter 3 * HALT $end
$var parameter 6 + HLT $end
$var parameter 3 , LOAD $end
$var parameter 6 - LW $end
$var parameter 6 . MUL $end
$var parameter 6 / OR $end
$var parameter 3 0 RM_ALU $end
$var parameter 3 1 RR_ALU $end
$var parameter 6 2 SLT $end
$var parameter 6 3 SLTI $end
$var parameter 3 4 STORE $end
$var parameter 6 5 SUB $end
$var parameter 6 6 SUBI $end
$var parameter 6 7 SW $end
$var reg 32 8 EX_MEM_ALUOut [31:0] $end
$var reg 32 9 EX_MEM_B [31:0] $end
$var reg 32 : EX_MEM_IR [31:0] $end
$var reg 1 ; EX_MEM_cond $end
$var reg 3 < EX_MEM_type [2:0] $end
$var reg 1 = HALTED $end
$var reg 32 > ID_EX_A [31:0] $end
$var reg 32 ? ID_EX_B [31:0] $end
$var reg 32 @ ID_EX_IR [31:0] $end
$var reg 32 A ID_EX_Imm [31:0] $end
$var reg 32 B ID_EX_NPC [31:0] $end
$var reg 3 C ID_EX_type [2:0] $end
$var reg 32 D IF_ID_IR [31:0] $end
$var reg 32 E IF_ID_NPC [31:0] $end
$var reg 32 F MEM_WB_ALUOut [31:0] $end
$var reg 32 G MEM_WB_IR [31:0] $end
$var reg 32 H MEM_WB_LMD [31:0] $end
$var reg 3 I MEM_WB_type [2:0] $end
$var reg 32 J PC [31:0] $end
$var reg 1 K TAKEN_BRANCH $end
$upscope $end
$upscope $end
$enddefinitions $end
$comment Show the parameter values. $end
$dumpall
b1001 7
b1011 6
b1 5
b11 4
b1100 3
b100 2
b0 1
b1 0
b11 /
b101 .
b1000 -
b10 ,
b111111 +
b101 *
b100 )
b1101 (
b1110 '
b10 &
b1010 %
b0 $
$end
#0
$dumpvars
0K
b0 J
bx I
bx H
bx G
bx F
bx E
bx D
bx C
bx B
bx A
bx @
bx ?
bx >
0=
bx <
x;
bx :
bx 9
bx 8
b11111 #
0"
0!
$end
#5
1!
#7
b1 J
b1 E
b101000000010100000000011001000 D
#10
0!
#15
b0 >
1"
#17
b1 C
b11001000 A
b101000000010100000000011001000 @
b1 B
b1010 ?
#20
0"
#25
1!
#27
b11001000 8
b1 <
b101000000010100000000011001000 :
b10 J
b10 E
b101000000000100000000000000001 D
#30
0!
#35
1"
#37
b11001000 F
b101000000010100000000011001000 G
b1 I
b1 A
b101000000000100000000000000001 @
b10 B
b10 ?
#40
0"
#45
1!
#47
b11 J
b11 E
b1110100101001010000000000000 D
b1 8
b101000000000100000000000000001 :
#50
0!
#55
1"
#57
b0 C
b11111111111111111010000000000000 A
b1110100101001010000000000000 @
b11 B
b10100 ?
b10100 >
b1 F
b101000000000100000000000000001 G
#60
0"
#65
1!
#67
b10100 8
b0 <
b1110100101001010000000000000 :
b100 J
b100 E
b100001010000110000000000000000 D
#70
0!
#75
1"
#77
b10100 F
b1110100101001010000000000000 G
b0 I
b10 C
b0 A
b100001010000110000000000000000 @
b100 B
b11 ?
b11001000 >
#80
0"
#85
1!
#87
b101 J
b101 E
b1110100101001010000000000000 D
b11 9
b11001000 8
b10 <
b100001010000110000000000000000 :
#90
0!
#95
1"
#97
b0 C
b11111111111111111010000000000000 A
b1110100101001010000000000000 @
b101 B
b10100 ?
b10100 >
b111 H
b100001010000110000000000000000 G
b10 I
#100
0"
#105
1!
#107
b10100 8
b0 <
b1110100101001010000000000000 :
b110 J
b110 E
b10100010000110001000000000000 D
#110
0!
#115
1"
#117
b1110100101001010000000000000 G
b0 I
b1000000000000 A
b10100010000110001000000000000 @
b110 B
b111 ?
b1 >
#120
0"
#125
1!
#127
b111 J
b111 E
b101100011000110000000000000001 D
b111 8
b10100010000110001000000000000 :
#130
0!
#135
1"
#137
b1 C
b1 A
b101100011000110000000000000001 @
b111 B
b111 >
b111 F
b10100010000110001000000000000 G
#140
0"
#145
1!
#147
b110 8
b1 <
b101100011000110000000000000001 :
b1000 J
b1000 E
b1110100101001010000000000000 D
#150
0!
#155
1"
#157
b110 F
b101100011000110000000000000001 G
b1 I
b0 C
b11111111111111111010000000000000 A
b1110100101001010000000000000 @
b1000 B
b10100 ?
b10100 >
#160
0"
#165
1!
#167
b1001 J
b1001 E
b110100011000001111111111111100 D
b10100 8
b0 <
b1110100101001010000000000000 :
#170
0!
#175
b0 ?
1"
#177
b100 C
b11111111111111111111111111111100 A
b110100011000001111111111111100 @
b1001 B
b110 >
b10100 F
b1110100101001010000000000000 G
b0 I
#180
0"
#185
1!
#187
0;
b101 8
b100 <
b110100011000001111111111111100 :
b1010 J
b1010 E
b100101010000101111111111111110 D
#190
0!
#195
1"
#197
b110100011000001111111111111100 G
b100 I
b11 C
b11111111111111111111111111111110 A
b100101010000101111111111111110 @
b1010 B
b111 ?
b11001000 >
#200
0"
#205
1!
#207
b110 J
b110 E
1K
b10100010000110001000000000000 D
b111 9
b11000110 8
b11 <
b100101010000101111111111111110 :
#210
0!
#215
1"
#217
b0 C
b1000000000000 A
b10100010000110001000000000000 @
b110 B
b110 ?
b111 >
b100101010000101111111111111110 G
b11 I
#220
0"
#225
1!
#227
b101010 8
0K
b0 <
b10100010000110001000000000000 :
b111 J
b111 E
b101100011000110000000000000001 D
#230
0!
#235
1"
#237
b101010 F
b10100010000110001000000000000 G
b0 I
b1 C
b1 A
b101100011000110000000000000001 @
b111 B
b110 >
#240
0"
#245
1!
#247
b1000 J
b1000 E
b1110100101001010000000000000 D
b101 8
b1 <
b101100011000110000000000000001 :
#250
0!
#255
1"
#257
b0 C
b11111111111111111010000000000000 A
b1110100101001010000000000000 @
b1000 B
b10100 ?
b10100 >
b101 F
b101100011000110000000000000001 G
b1 I
#260
0"
#265
1!
#267
b10100 8
b0 <
b1110100101001010000000000000 :
b1001 J
b1001 E
b110100011000001111111111111100 D
#270
0!
#275
b0 ?
1"
#277
b10100 F
b1110100101001010000000000000 G
b0 I
b100 C
b11111111111111111111111111111100 A
b110100011000001111111111111100 @
b1001 B
b101 >
#280
0"
#285
1!
#287
b1010 J
b1010 E
b100101010000101111111111111110 D
b101 8
b100 <
b110100011000001111111111111100 :
#290
0!
#295
1"
#297
b11 C
b11111111111111111111111111111110 A
b100101010000101111111111111110 @
b1010 B
b101010 ?
b11001000 >
b110100011000001111111111111100 G
b100 I
#300
0"
#305
1!
#307
b101010 9
b11000110 8
b11 <
b100101010000101111111111111110 :
b110 J
b110 E
0K
b10100010000110001000000000000 D
#310
0!
#315
1"
#317
b100101010000101111111111111110 G
b11 I
b0 C
b1000000000000 A
b10100010000110001000000000000 @
b110 B
b101 ?
b101010 >
#320
0"
#325
1!
#327
b111 J
b111 E
b101100011000110000000000000001 D
b11010010 8
b0 <
b10100010000110001000000000000 :
#330
0!
#335
1"
#337
b1 C
b1 A
b101100011000110000000000000001 @
b111 B
b101 >
b11010010 F
b10100010000110001000000000000 G
b0 I
#340
0"
#345
1!
#347
b100 8
b1 <
b101100011000110000000000000001 :
b1000 J
b1000 E
b1110100101001010000000000000 D
#350
0!
#355
1"
#357
b100 F
b101100011000110000000000000001 G
b1 I
b0 C
b11111111111111111010000000000000 A
b1110100101001010000000000000 @
b1000 B
b10100 ?
b10100 >
#360
0"
#365
1!
#367
b1001 J
b1001 E
b110100011000001111111111111100 D
b10100 8
b0 <
b1110100101001010000000000000 :
#370
0!
#375
b0 ?
1"
#377
b100 C
b11111111111111111111111111111100 A
b110100011000001111111111111100 @
b1001 B
b100 >
b10100 F
b1110100101001010000000000000 G
b0 I
#380
0"
#385
1!
#387
b101 8
b100 <
b110100011000001111111111111100 :
b1010 J
b1010 E
b100101010000101111111111111110 D
#390
0!
#395
1"
#397
b110100011000001111111111111100 G
b100 I
b11 C
b11111111111111111111111111111110 A
b100101010000101111111111111110 @
b1010 B
b11010010 ?
b11001000 >
#400
0"
#405
1!
#407
b110 J
b110 E
1K
b10100010000110001000000000000 D
b11010010 9
b11000110 8
b11 <
b100101010000101111111111111110 :
#410
0!
#415
1"
#417
b0 C
b1000000000000 A
b10100010000110001000000000000 @
b110 B
b100 ?
b11010010 >
b100101010000101111111111111110 G
b11 I
#420
0"
#425
1!
#427
b1101001000 8
0K
b0 <
b10100010000110001000000000000 :
b111 J
b111 E
b101100011000110000000000000001 D
#430
0!
#435
1"
#437
b1101001000 F
b10100010000110001000000000000 G
b0 I
b1 C
b1 A
b101100011000110000000000000001 @
b111 B
b100 >
#440
0"
#445
1!
#447
b1000 J
b1000 E
b1110100101001010000000000000 D
b11 8
b1 <
b101100011000110000000000000001 :
#450
0!
#455
1"
#457
b0 C
b11111111111111111010000000000000 A
b1110100101001010000000000000 @
b1000 B
b10100 ?
b10100 >
b11 F
b101100011000110000000000000001 G
b1 I
#460
0"
#465
1!
#467
b10100 8
b0 <
b1110100101001010000000000000 :
b1001 J
b1001 E
b110100011000001111111111111100 D
#470
0!
#475
b0 ?
1"
#477
b10100 F
b1110100101001010000000000000 G
b0 I
b100 C
b11111111111111111111111111111100 A
b110100011000001111111111111100 @
b1001 B
b11 >
#480
0"
#485
1!
#487
b1010 J
b1010 E
b100101010000101111111111111110 D
b101 8
b100 <
b110100011000001111111111111100 :
#490
0!
#495
1"
#497
b11 C
b11111111111111111111111111111110 A
b100101010000101111111111111110 @
b1010 B
b1101001000 ?
b11001000 >
b110100011000001111111111111100 G
b100 I
#500
0"
#505
1!
#507
b1101001000 9
b11000110 8
b11 <
b100101010000101111111111111110 :
b110 J
b110 E
0K
b10100010000110001000000000000 D
#510
0!
#515
1"
#517
b100101010000101111111111111110 G
b11 I
b0 C
b1000000000000 A
b10100010000110001000000000000 @
b110 B
b11 ?
b1101001000 >
#520
0"
#525
1!
#527
b111 J
b111 E
b101100011000110000000000000001 D
b100111011000 8
b0 <
b10100010000110001000000000000 :
#530
0!
#535
1"
#537
b1 C
b1 A
b101100011000110000000000000001 @
b111 B
b11 >
b100111011000 F
b10100010000110001000000000000 G
b0 I
#540
0"
#545
1!
#547
b10 8
b1 <
b101100011000110000000000000001 :
b1000 J
b1000 E
b1110100101001010000000000000 D
#550
0!
#555
1"
#557
b10 F
b101100011000110000000000000001 G
b1 I
b0 C
b11111111111111111010000000000000 A
b1110100101001010000000000000 @
b1000 B
b10100 ?
b10100 >
#560
0"
#565
1!
#567
b1001 J
b1001 E
b110100011000001111111111111100 D
b10100 8
b0 <
b1110100101001010000000000000 :
#570
0!
#575
b0 ?
1"
#577
b100 C
b11111111111111111111111111111100 A
b110100011000001111111111111100 @
b1001 B
b10 >
b10100 F
b1110100101001010000000000000 G
b0 I
#580
0"
#585
1!
#587
b101 8
b100 <
b110100011000001111111111111100 :
b1010 J
b1010 E
b100101010000101111111111111110 D
#590
0!
#595
1"
#597
b110100011000001111111111111100 G
b100 I
b11 C
b11111111111111111111111111111110 A
b100101010000101111111111111110 @
b1010 B
b100111011000 ?
b11001000 >
#600
0"
#605
1!
#607
b110 J
b110 E
1K
b10100010000110001000000000000 D
b100111011000 9
b11000110 8
b11 <
b100101010000101111111111111110 :
#610
0!
#615
1"
#617
b0 C
b1000000000000 A
b10100010000110001000000000000 @
b110 B
b10 ?
b100111011000 >
b100101010000101111111111111110 G
b11 I
#620
0"
#625
1!
#627
b1001110110000 8
0K
b0 <
b10100010000110001000000000000 :
b111 J
b111 E
b101100011000110000000000000001 D
#630
0!
#635
1"
#637
b1001110110000 F
b10100010000110001000000000000 G
b0 I
b1 C
b1 A
b101100011000110000000000000001 @
b111 B
b10 >
#640
0"
#645
1!
#647
b1000 J
b1000 E
b1110100101001010000000000000 D
b1 8
b1 <
b101100011000110000000000000001 :
#650
0!
#655
1"
#657
b0 C
b11111111111111111010000000000000 A
b1110100101001010000000000000 @
b1000 B
b10100 ?
b10100 >
b1 F
b101100011000110000000000000001 G
b1 I
#660
0"
#665
1!
#667
b10100 8
b0 <
b1110100101001010000000000000 :
b1001 J
b1001 E
b110100011000001111111111111100 D
#670
0!
#675
b0 ?
1"
#677
b10100 F
b1110100101001010000000000000 G
b0 I
b100 C
b11111111111111111111111111111100 A
b110100011000001111111111111100 @
b1001 B
b1 >
#680
0"
#685
1!
#687
b1010 J
b1010 E
b100101010000101111111111111110 D
b101 8
b100 <
b110100011000001111111111111100 :
#690
0!
#695
1"
#697
b11 C
b11111111111111111111111111111110 A
b100101010000101111111111111110 @
b1010 B
b1001110110000 ?
b11001000 >
b110100011000001111111111111100 G
b100 I
#700
0"
#705
1!
#707
b1001110110000 9
b11000110 8
b11 <
b100101010000101111111111111110 :
b110 J
b110 E
0K
b10100010000110001000000000000 D
#710
0!
#715
1"
#717
b100101010000101111111111111110 G
b11 I
b0 C
b1000000000000 A
b10100010000110001000000000000 @
b110 B
b1 ?
b1001110110000 >
#720
0"
#725
1!
#727
b111 J
b111 E
b101100011000110000000000000001 D
b1001110110000 8
b0 <
b10100010000110001000000000000 :
#730
0!
#735
1"
#737
b1 C
b1 A
b101100011000110000000000000001 @
b111 B
b1 >
b1001110110000 F
b10100010000110001000000000000 G
b0 I
#740
0"
#745
1!
#747
b0 8
b1 <
b101100011000110000000000000001 :
b1000 J
b1000 E
b1110100101001010000000000000 D
#750
0!
#755
1"
#757
b0 F
b101100011000110000000000000001 G
b1 I
b0 C
b11111111111111111010000000000000 A
b1110100101001010000000000000 @
b1000 B
b10100 ?
b10100 >
#760
0"
#765
1!
#767
b1001 J
b1001 E
b110100011000001111111111111100 D
b10100 8
b0 <
b1110100101001010000000000000 :
#770
0!
#775
b0 ?
1"
#777
b100 C
b11111111111111111111111111111100 A
b110100011000001111111111111100 @
b1001 B
b0 >
b10100 F
b1110100101001010000000000000 G
b0 I
#780
0"
#785
1!
#787
1;
b101 8
b100 <
b110100011000001111111111111100 :
b1010 J
b1010 E
b100101010000101111111111111110 D
#790
0!
#795
1"
#797
b110100011000001111111111111100 G
b100 I
b11 C
b11111111111111111111111111111110 A
b100101010000101111111111111110 @
b1010 B
b1001110110000 ?
b11001000 >
#800
0"
#805
1!
#807
b1011 J
b1011 E
b11111100000000000000000000000000 D
b11000110 8
b11 <
b100101010000101111111111111110 :
#810
0!
#815
b0 ?
b0 >
1"
#817
b101 C
b0 A
b11111100000000000000000000000000 @
b1011 B
b100101010000101111111111111110 G
b11 I
#820
0"
#825
1!
#827
b101 <
b11111100000000000000000000000000 :
b1100 J
b1100 E
bx D
#830
0!
#835
1"
#837
b11111100000000000000000000000000 G
b101 I
bx A
bx @
b1100 B
bx ?
bx >
#840
0"
#845
1!
#847
b1101 J
b1101 E
bx :
1=
